trench/__init__.py
trench/admin.py
trench/apps.py
trench/exceptions.py
trench/models.py
trench/responses.py
trench/serializers.py
trench/settings.py
trench/utils.py
trench/backends/__init__.py
trench/backends/application.py
trench/backends/base.py
trench/backends/basic_mail.py
trench/backends/provider.py
trench/backends/sms_api.py
trench/backends/twilio.py
trench/backends/yubikey.py
trench/command/__init__.py
trench/command/activate_mfa_method.py
trench/command/authenticate_second_factor.py
trench/command/authenticate_user.py
trench/command/create_mfa_method.py
trench/command/create_otp.py
trench/command/create_secret.py
trench/command/deactivate_mfa_method.py
trench/command/generate_backup_codes.py
trench/command/remove_backup_code.py
trench/command/replace_mfa_method_backup_codes.py
trench/command/set_primary_mfa_method.py
trench/command/validate_backup_code.py
trench/locale/de/LC_MESSAGES/django.mo
trench/locale/de/LC_MESSAGES/django.po
trench/locale/en/LC_MESSAGES/django.mo
trench/locale/en/LC_MESSAGES/django.po
trench/locale/pl/LC_MESSAGES/django.mo
trench/locale/pl/LC_MESSAGES/django.po
trench/migrations/0001_initial.py
trench/migrations/0002_auto_20190111_1403.py
trench/migrations/0003_auto_20190213_2330.py
trench/migrations/__init__.py
trench/query/__init__.py
trench/query/get_mfa_config_by_name.py
trench/templates/trench/backends/email/code.html
trench/templates/trench/backends/email/code.txt
trench/urls/__init__.py
trench/urls/authtoken.py
trench/urls/base.py
trench/urls/jwt.py
trench/views/__init__.py
trench/views/authtoken.py
trench/views/base.py
trench/views/jwt.py
django_trench-0.3.1.dist-info/AUTHORS
django_trench-0.3.1.dist-info/LICENSE
django_trench-0.3.1.dist-info/METADATA
django_trench-0.3.1.dist-info/WHEEL
django_trench-0.3.1.dist-info/top_level.txt
django_trench-0.3.1.dist-info/RECORD
